altimate_models/__init__.py
altimate_models/base/__init__.py
altimate_models/base/dialect.py
altimate_models/base/extractor.py
altimate_models/base/metadata_profiler.py
altimate_models/base/profiler.py
altimate_models/base/source.py
altimate_models/base/ssh_source.py
altimate_models/base/utils.py
altimate_models/config_factory.py
altimate_models/constants.py
altimate_models/duckdb/__init__.py
altimate_models/duckdb/dialect.py
altimate_models/duckdb/extractor.py
altimate_models/duckdb/metadata_profiler.py
altimate_models/duckdb/profiler.py
altimate_models/postgresql/__init__.py
altimate_models/postgresql/dialect.py
altimate_models/postgresql/extractor.py
altimate_models/postgresql/profiler.py
altimate_models/postgresql/source.py
altimate_models/s3/__init__.py
altimate_models/s3/csv_source_dialect.py
altimate_models/s3/extractor.py
altimate_models/s3/json_source_dialect.py
altimate_models/s3/parquet_source_dialect.py
altimate_models/s3/profiler.py
altimate_models/s3/source.py
altimate_models/s3/utils.py
altimate_models/shared_models.py
altimate_models/snowflake/__init__.py
altimate_models/snowflake/dialect.py
altimate_models/snowflake/profiler.py
altimate_models/snowflake/source.py
altimate_models/tableau/extractor.py
altimate_models/tableau/source.py
altimate_profiler/__init__.py
altimate_profiler/builders/__init__.py
altimate_profiler/builders/base_builder.py
altimate_profiler/builders/column_metrics_query_builder.py
altimate_profiler/builders/custom_query_builder.py
altimate_profiler/builders/metadata_query_builder.py
altimate_profiler/builders/performance_query_builder.py
altimate_profiler/builders/s3_column_metrics_query_builder.py
altimate_profiler/builders/s3_schema_query_builder.py
altimate_profiler/builders/s3_table_query_builder.py
altimate_profiler/builders/schema_query_builder.py
altimate_profiler/builders/table_query_builder.py
altimate_profiler/builders/utils.py
altimate_profiler/exceptions.py
altimate_profiler/factory.py
altimate_profiler/main.py
altimate_dataminion-0.1.1.dist-info/METADATA
altimate_dataminion-0.1.1.dist-info/WHEEL
altimate_dataminion-0.1.1.dist-info/RECORD
