Metadata-Version: 2.4
Name: altimate-dataminion
Version: 0.1.1
Summary: Internal package. Use this at your own risk, support not guaranteed
Author: Altimate Inc
Author-email: info@altimate.ai
Requires-Python: >=3.10,<4.0
Classifier: Programming Language :: Python :: 3
Classifier: Programming Language :: Python :: 3.10
Classifier: Programming Language :: Python :: 3.11
Classifier: Programming Language :: Python :: 3.12
Classifier: Programming Language :: Python :: 3.13
Classifier: Programming Language :: Python :: 3.14
Requires-Dist: black (>=23.3,<25.0)
Requires-Dist: duckdb (==1.1.2)
Requires-Dist: isort (>=5.12.0,<6.0.0)
Requires-Dist: jsonschema (>=4.17.3,<5.0.0)
Requires-Dist: mypy (>=1.2.0,<2.0.0)
Requires-Dist: numpy (>=1.24.3,<2.0.0)
Requires-Dist: pandas (>=2.0.1,<3.0.0)
Requires-Dist: psycopg2-binary (==2.9.5)
Requires-Dist: pydantic (>=2.11.0,<3.0.0)
Requires-Dist: pytest (>=7.3.1,<8.0.0)
Requires-Dist: python-dotenv (>=1.0.0,<2.0.0)
Requires-Dist: snowflake-connector-python (>=3.0.3,<4.0.0)
Requires-Dist: snowflake-sqlalchemy (>=1.4.7,<2.0.0)
Requires-Dist: sqlalchemy[mypy] (<2.0.0)
Requires-Dist: sshtunnel (>=0.4.0,<0.5.0)
Requires-Dist: tableauserverclient (>=0.38,<0.39)
